coconext/__init__.py
coconext/_concurrent_waiters.py
coconext/_synchronization_primitives.py
coconext/_task_manager.py
coconext/py.typed
coconext/queue.py
coconext/simtime.py
coconext/triggers.py
coconext-0.2.2.dist-info/licenses/LICENSE
coconext-0.2.2.dist-info/METADATA
coconext-0.2.2.dist-info/WHEEL
coconext-0.2.2.dist-info/top_level.txt
coconext-0.2.2.dist-info/RECORD
