Metadata-Version: 2.4
Name: coconext
Version: 0.2.2
Summary: Features for future versions of cocotb
Author-email: Kaleb Barrett <dev.ktbarrett@gmail.com>
Maintainer-email: Kaleb Barrett <dev.ktbarrett@gmail.com>
License: BSD-3-Clause
Project-URL: Repository, https://github.com/ktbarrett/coconext.git
Project-URL: Bug Tracker, https://github.com/ktbarrett/coconext/issues
Requires-Python: >=3.8
License-File: LICENSE
Requires-Dist: cocotb~=2.0b
Requires-Dist: exceptiongroup; python_version < "3.11"
Dynamic: license-file
